{"一": {"name": "", "context_name": null, "hash": "6294e2f7581a8cd15e0ce92fd1011bf5", "stamp": 1737304737.5005944, "version": "0.0.4"}, "c-rec-258041127917": {"name": "1-80", "context_name": "1", "hash": "9f9651151c0b5c0b6a39b00d821a76a8", "stamp": 1737304737.5005944, "version": "0.0.4"}, "図": {"name": "", "context_name": null, "hash": "e6228d343bd778b306a90501e7abc011", "stamp": 1737304737.5005944, "version": "0.0.4"}, "c-rec-125935416005": {"name": "81-160", "context_name": "1", "hash": "21ac4b589f9cdae3e7cf55905e9b8144", "stamp": 1737304737.5005944, "version": "0.0.4"}, "radical": {"name": "radical", "context_name": null, "hash": "2498c496c6ccdaa8656a1eaf88650623", "stamp": 1737304737.5005944, "version": "0.0.4"}, "二": {"name": "", "context_name": null, "hash": "ffd5df40ee6e5feea3f6007afd8cf9b8", "stamp": 1737304737.5005944, "version": "0.0.4"}, "工": {"name": "", "context_name": null, "hash": "d4d61247f58d817e5a787a8c5099cd24", "stamp": 1737304737.5005944, "version": "0.0.4"}, "三": {"name": "", "context_name": null, "hash": "8d42f82145bf5f6ab7ae8655139e8d2a", "stamp": 1737304737.5005944, "version": "0.0.4"}, "教": {"name": "", "context_name": null, "hash": "81999cb27720903459744c4b04ee10be", "stamp": 1737304737.5005944, "version": "0.0.4"}, "四": {"name": "", "context_name": null, "hash": "1ea90ec73b03b92ce9d5e30ec4cc2af2", "stamp": 1737304737.5005944, "version": "0.0.4"}, "五": {"name": "", "context_name": null, "hash": "2101e85811379d15befebf340bd0c675", "stamp": 1737304737.5005944, "version": "0.0.4"}, "六": {"name": "", "context_name": null, "hash": "fd3f1bb15bd46f9f37a1c0335d9905b2", "stamp": 1737304737.5005944, "version": "0.0.4"}, "七": {"name": "", "context_name": null, "hash": "68d8ef893ed50e7426cc54f274899ae4", "stamp": 1737304737.5005944, "version": "0.0.4"}, "八": {"name": "", "context_name": null, "hash": "3cf58639aaac6cdf1bc96d96838e716d", "stamp": 1737304737.5005944, "version": "0.0.4"}, "九": {"name": "", "context_name": null, "hash": "971bd3bbe4d58ca1c7365b637812f25f", "stamp": 1737304737.5005944, "version": "0.0.4"}, "十": {"name": "", "context_name": null, "hash": "d63f96afe9d3f7a3d5eb6389bd5d702d", "stamp": 1737304737.5005944, "version": "0.0.4"}, "百": {"name": "", "context_name": null, "hash": "60bfbb3242a4ad246923baec25212001", "stamp": 1737304737.5005944, "version": "0.0.4"}, "千": {"name": "", "context_name": null, "hash": "a87bb7a6957f3a6b21c00934a2050bef", "stamp": 1737304737.5005944, "version": "0.0.4"}, "上": {"name": "", "context_name": null, "hash": "8f94ec7caa911154a84b1fe28f749d14", "stamp": 1737304737.5005944, "version": "0.0.4"}, "下": {"name": "", "context_name": null, "hash": "554073ca8707a8c68a4504f4a5e8680b", "stamp": 1737304737.5005944, "version": "0.0.4"}, "中": {"name": "", "context_name": null, "hash": "a5219b9b54ba3fabf73cd9b1cd7545fe", "stamp": 1737304737.5005944, "version": "0.0.4"}, "大": {"name": "", "context_name": null, "hash": "a88f5a932fd4ec7213b282859b1de19d", "stamp": 1737304737.5005944, "version": "0.0.4"}, "小": {"name": "", "context_name": null, "hash": "25238c73dcb0bd048e84f7a16da87f4b", "stamp": 1737304737.5005944, "version": "0.0.4"}, "月": {"name": "", "context_name": null, "hash": "12fccb75559786c53f8b630142ce62d5", "stamp": 1737304737.5005944, "version": "0.0.4"}, "左": {"name": "", "context_name": null, "hash": "dee606b2ab8bd36af0c3787e81fe6647", "stamp": 1737304737.5005944, "version": "0.0.4"}, "右": {"name": "", "context_name": null, "hash": "f1f2b28b6da990d5a2545dd91eea5552", "stamp": 1737304737.5005944, "version": "0.0.4"}, "晴": {"name": "", "context_name": null, "hash": "da08d84b3494a3fd8039d88b582ce528", "stamp": 1737304737.5005944, "version": "0.0.4"}, "思": {"name": "", "context_name": null, "hash": "afbfad37040ec12d8028791f78fe806a", "stamp": 1737304737.5005944, "version": "0.0.4"}, "考": {"name": "", "context_name": null, "hash": "3440ef12f044a40255ea93b464c97cf6", "stamp": 1737304737.5005944, "version": "0.0.4"}, "知": {"name": "", "context_name": null, "hash": "c24b65dcae949435c85e1906ed3fbd71", "stamp": 1737304737.5005944, "version": "0.0.4"}, "才": {"name": "", "context_name": null, "hash": "6ae0f60e90742d52ee9bd36f75ee3a78", "stamp": 1737304737.5005944, "version": "0.0.4"}, "理": {"name": "", "context_name": null, "hash": "c24d244d8ae182a19d503c82a985fe8c", "stamp": 1737304737.5005944, "version": "0.0.4"}, "算": {"name": "", "context_name": null, "hash": "f9af6563d2b767ca82bdf21775474ddf", "stamp": 1737304737.5005944, "version": "0.0.4"}, "作": {"name": "", "context_name": null, "hash": "aff34dbb3ad2dbac54c5586cfe6da237", "stamp": 1737304737.5005944, "version": "0.0.4"}, "元": {"name": "", "context_name": null, "hash": "2643459a0903791d95637504cd984060", "stamp": 1737304737.5005944, "version": "0.0.4"}, "食": {"name": "", "context_name": null, "hash": "502e157e868ebc77185f6d2a03f7240e", "stamp": 1737304737.5005944, "version": "0.0.4"}, "肉": {"name": "", "context_name": null, "hash": "482fee188579eeb6323718cb4176e53a", "stamp": 1737304737.5005944, "version": "0.0.4"}, "馬": {"name": "", "context_name": null, "hash": "dc7ccfd2edfb9c764c01872ea7c41b95", "stamp": 1737304737.5005944, "version": "0.0.4"}, "牛": {"name": "", "context_name": null, "hash": "70f0aa67ec68f7960f1cac5ba5cb7732", "stamp": 1737304737.5005944, "version": "0.0.4"}, "魚": {"name": "", "context_name": null, "hash": "83cb2167ba6fb05b929ea72afe27d6d4", "stamp": 1737304737.5005944, "version": "0.0.4"}, "鳥": {"name": "", "context_name": null, "hash": "a2bc840f745c2c04f35813988f9008a8", "stamp": 1737304737.5005944, "version": "0.0.4"}, "羽": {"name": "", "context_name": null, "hash": "6b25b923d3ddfea69226e336f2d6ea67", "stamp": 1737304737.5005944, "version": "0.0.4"}, "鳴": {"name": "", "context_name": null, "hash": "42f57434c2a7e9e27bf16439ec7a6b26", "stamp": 1737304737.5005944, "version": "0.0.4"}, "麦": {"name": "", "context_name": null, "hash": "80eac801f60ced0f728c352a49f354c1", "stamp": 1737304737.5005944, "version": "0.0.4"}, "米": {"name": "", "context_name": null, "hash": "c16a3d7d0bb549ce244e69b89bbc8cd8", "stamp": 1737304737.5005944, "version": "0.0.4"}, "茶": {"name": "", "context_name": null, "hash": "bfb485422528fe3b2de4428f8a185f2a", "stamp": 1737304737.5005944, "version": "0.0.4"}, "色": {"name": "", "context_name": null, "hash": "c4d360d3704d9627e221a219d5437612", "stamp": 1737304737.5005944, "version": "0.0.4"}}